this_import_reader/__init__.py
this_import_reader/__main__.py
this_import_reader/feed.py
this_import_reader/viewer.py
this_import_reader/pyarmor_runtime_000000/__init__.py
this_import_reader-3.0.0.dist-info/METADATA
this_import_reader-3.0.0.dist-info/WHEEL
this_import_reader-3.0.0.dist-info/entry_points.txt
this_import_reader-3.0.0.dist-info/top_level.txt
this_import_reader-3.0.0.dist-info/RECORD
